pernaf/__init__.py
pernaf/naf.py
pernaf/utils/__init__.py
pernaf/utils/core.py
pernaf/utils/prioritised_experience_replay.py
pernaf/utils/segment_tree.py
pernaf/utils/statistic.py
pernaf/utils/sum_tree.py
pernaf-0.0.14.dist-info/LICENSE
pernaf-0.0.14.dist-info/METADATA
pernaf-0.0.14.dist-info/WHEEL
pernaf-0.0.14.dist-info/top_level.txt
pernaf-0.0.14.dist-info/RECORD
