Metadata-Version: 2.1
Name: pernaf
Version: 0.0.14
Summary: An implementation of the Normalized Advantage Function Reinforcement Learning Algorithm with Prioritized Experience Replay
Home-page: https://github.com/MathPhysSim/PER-NAF
Author: Simon Hirlaender
Author-email: simon.hirlaender@cern.ch
License: UNKNOWN
Platform: UNKNOWN
Classifier: Programming Language :: Python :: 3
Classifier: License :: OSI Approved :: MIT License
Classifier: Operating System :: OS Independent
Requires-Python: >=3.6
Requires-Dist: tensorflow (==1.14)
Requires-Dist: numpy
Requires-Dist: gym
